{
  "Sinif_Sube": [
    {
      "value": "5A",
      "text": "5. Sınıf / A Şubesi"
    },
    {
      "value": "5B",
      "text": "5. Sınıf / B Şubesi"
    },
    {
      "value": "5C",
      "text": "5. Sınıf / C Şubesi"
    },
    {
      "value": "6A",
      "text": "6. Sınıf / A Şubesi"
    },
    {
      "value": "6B",
      "text": "6. Sınıf / B Şubesi"
    },
    {
      "value": "6C",
      "text": "6. Sınıf / C Şubesi"
    },
    {
      "value": "7A",
      "text": "7. Sınıf / A Şubesi"
    },
    {
      "value": "7B",
      "text": "7. Sınıf / B Şubesi"
    },
    {
      "value": "7C",
      "text": "7. Sınıf / C Şubesi"
    },
    {
      "value": "8A",
      "text": "8. Sınıf / A Şubesi"
    },
    {
      "value": "8B",
      "text": "8. Sınıf / B Şubesi"
    },
    {
      "value": "8C",
      "text": "8. Sınıf / C Şubesi"
    }
  ],
  "Ogrenci_5. Sınıf _ A Şubesi": [
    {
      "Tc Kimlik": "99889813498",
      "Ad": "ABDULİLLAH",
      "Soyad": "ELCASIM",
      "Okul No": "10",
      "Sinif Sube": "5A"
    },
    {
      "Tc Kimlik": "33338302386",
      "Ad": "ABDULKADİR",
      "Soyad": "MURAT",
      "Okul No": "9",
      "Sinif Sube": "5A"
    },
    {
      "Tc Kimlik": "27008283044",
      "Ad": "AHMET METE",
      "Soyad": "ÇİFTÇİ",
      "Okul No": "555",
      "Sinif Sube": "5A"
    },
    {
      "Tc Kimlik": "48898783612",
      "Ad": "ALİ ARDA",
      "Soyad": "KILIÇ",
      "Okul No": "260",
      "Sinif Sube": "5A"
    },
    {
      "Tc Kimlik": "39641091856",
      "Ad": "AMİNE ŞEYMA",
      "Soyad": "YEŞİLBAŞ",
      "Okul No": "88",
      "Sinif Sube": "5A"
    },
    {
      "Tc Kimlik": "29582427234",
      "Ad": "AYHAN ENES",
      "Soyad": "KARADAŞ",
      "Okul No": "188",
      "Sinif Sube": "5A"
    },
    {
      "Tc Kimlik": "99737093928",
      "Ad": "AYŞE",
      "Soyad": "ELHALAF",
      "Okul No": "92",
      "Sinif Sube": "5A"
    },
    {
      "Tc Kimlik": "99437035044",
      "Ad": "BEHÇED",
      "Soyad": "YASİN",
      "Okul No": "97",
      "Sinif Sube": "5A"
    },
    {
      "Tc Kimlik": "64672257582",
      "Ad": "CANAN SU",
      "Soyad": "AKINCI",
      "Okul No": "375",
      "Sinif Sube": "5A"
    },
    {
      "Tc Kimlik": "59554428518",
      "Ad": "CANER",
      "Soyad": "DEMİR",
      "Okul No": "379",
      "Sinif Sube": "5A"
    },
    {
      "Tc Kimlik": "14960914284",
      "Ad": "DİLAN",
      "Soyad": "TUNGAÇ",
      "Okul No": "126",
      "Sinif Sube": "5A"
    },
    {
      "Tc Kimlik": "99196541992",
      "Ad": "ESMA",
      "Soyad": "ELALİ",
      "Okul No": "191",
      "Sinif Sube": "5A"
    },
    {
      "Tc Kimlik": "99277902780",
      "Ad": "GAZALE",
      "Soyad": "YASİN",
      "Okul No": "154",
      "Sinif Sube": "5A"
    },
    {
      "Tc Kimlik": "99025825842",
      "Ad": "HAMZA",
      "Soyad": "UMAR",
      "Okul No": "314",
      "Sinif Sube": "5A"
    },
    {
      "Tc Kimlik": "51802686770",
      "Ad": "HİRANUR",
      "Soyad": "EROĞLU",
      "Okul No": "381",
      "Sinif Sube": "5A"
    },
    {
      "Tc Kimlik": "34394266940",
      "Ad": "KÜBRA",
      "Soyad": "ASLAN",
      "Okul No": "426",
      "Sinif Sube": "5A"
    },
    {
      "Tc Kimlik": "25574560958",
      "Ad": "MAİL",
      "Soyad": "SERİN",
      "Okul No": "391",
      "Sinif Sube": "5A"
    },
    {
      "Tc Kimlik": "30110409110",
      "Ad": "MUHAMMED ARDA",
      "Soyad": "İMRAK",
      "Okul No": "462",
      "Sinif Sube": "5A"
    },
    {
      "Tc Kimlik": "37211172790",
      "Ad": "MÜSLÜM ARAS",
      "Soyad": "KARTAL",
      "Okul No": "507",
      "Sinif Sube": "5A"
    },
    {
      "Tc Kimlik": "99905184106",
      "Ad": "NEHİT",
      "Soyad": "DERVİŞ",
      "Okul No": "515",
      "Sinif Sube": "5A"
    },
    {
      "Tc Kimlik": "99590381408",
      "Ad": "NERMİN",
      "Soyad": "GASİS",
      "Okul No": "517",
      "Sinif Sube": "5A"
    },
    {
      "Tc Kimlik": "25448564570",
      "Ad": "TUANA İREM",
      "Soyad": "GÜZEL",
      "Okul No": "597",
      "Sinif Sube": "5A"
    },
    {
      "Tc Kimlik": "51097710112",
      "Ad": "UĞUR",
      "Soyad": "DOĞAN",
      "Okul No": "181",
      "Sinif Sube": "5A"
    },
    {
      "Tc Kimlik": "99242901534",
      "Ad": "VEFA",
      "Soyad": "EL NAHSAN",
      "Okul No": "248",
      "Sinif Sube": "5A"
    }
  ],
  "Ogrenci_5. Sınıf _ B Şubesi": [
    {
      "Tc Kimlik": "39563094492",
      "Ad": "AHMET",
      "Soyad": "POLAT",
      "Okul No": "5",
      "Sinif Sube": "5B"
    },
    {
      "Tc Kimlik": "99244935230",
      "Ad": "BİLAL",
      "Soyad": "GASİS",
      "Okul No": "111",
      "Sinif Sube": "5B"
    },
    {
      "Tc Kimlik": "43360967446",
      "Ad": "DENİZ",
      "Soyad": "KARADAĞ",
      "Okul No": "118",
      "Sinif Sube": "5B"
    },
    {
      "Tc Kimlik": "99224183750",
      "Ad": "DERİN",
      "Soyad": "NASEN",
      "Okul No": "502",
      "Sinif Sube": "5B"
    },
    {
      "Tc Kimlik": "99427549964",
      "Ad": "DIYALA",
      "Soyad": "HALIL",
      "Okul No": "43",
      "Sinif Sube": "5B"
    },
    {
      "Tc Kimlik": "44224939074",
      "Ad": "ECRİN",
      "Soyad": "OKLUER",
      "Okul No": "128",
      "Sinif Sube": "5B"
    },
    {
      "Tc Kimlik": "37925148852",
      "Ad": "ELİF",
      "Soyad": "KANIKARA",
      "Okul No": "132",
      "Sinif Sube": "5B"
    },
    {
      "Tc Kimlik": "29423432694",
      "Ad": "EMİN",
      "Soyad": "KARADAL",
      "Okul No": "137",
      "Sinif Sube": "5B"
    },
    {
      "Tc Kimlik": "64918249340",
      "Ad": "EMİNE SULTAN",
      "Soyad": "ŞİNİKÇİ",
      "Okul No": "140",
      "Sinif Sube": "5B"
    },
    {
      "Tc Kimlik": "54661590714",
      "Ad": "ESMA",
      "Soyad": "ÖZUÇAK",
      "Okul No": "170",
      "Sinif Sube": "5B"
    },
    {
      "Tc Kimlik": "60019412508",
      "Ad": "HAMZA",
      "Soyad": "YILDIRIM",
      "Okul No": "407",
      "Sinif Sube": "5B"
    },
    {
      "Tc Kimlik": "22037678106",
      "Ad": "KENAN",
      "Soyad": "CANLI",
      "Okul No": "422",
      "Sinif Sube": "5B"
    },
    {
      "Tc Kimlik": "99185895914",
      "Ad": "MERVE",
      "Soyad": "DEDEN",
      "Okul No": "276",
      "Sinif Sube": "5B"
    },
    {
      "Tc Kimlik": "28967448086",
      "Ad": "MUHAMMED RESÜL",
      "Soyad": "KIRMIZI",
      "Okul No": "369",
      "Sinif Sube": "5B"
    },
    {
      "Tc Kimlik": "37493163196",
      "Ad": "MUHAMMET",
      "Soyad": "DEMİRCİUŞAĞI",
      "Okul No": "497",
      "Sinif Sube": "5B"
    },
    {
      "Tc Kimlik": "39692090020",
      "Ad": "MÜSLÜM AYAZ",
      "Soyad": "GÖKTAŞ",
      "Okul No": "560",
      "Sinif Sube": "5B"
    },
    {
      "Tc Kimlik": "99731167946",
      "Ad": "RAHAF",
      "Soyad": "TÜRKMANİ",
      "Okul No": "540",
      "Sinif Sube": "5B"
    },
    {
      "Tc Kimlik": "99365212456",
      "Ad": "RAŞE",
      "Soyad": "MUHAMMED",
      "Okul No": "550",
      "Sinif Sube": "5B"
    },
    {
      "Tc Kimlik": "99014218228",
      "Ad": "SABAH",
      "Soyad": "MUHAMMED",
      "Okul No": "578",
      "Sinif Sube": "5B"
    },
    {
      "Tc Kimlik": "67852151410",
      "Ad": "SABRİYE NUR",
      "Soyad": "ÖZALTAY",
      "Okul No": "587",
      "Sinif Sube": "5B"
    },
    {
      "Tc Kimlik": "37997146770",
      "Ad": "SALİH",
      "Soyad": "SERİN",
      "Okul No": "591",
      "Sinif Sube": "5B"
    },
    {
      "Tc Kimlik": "57709489728",
      "Ad": "ŞİRVAN",
      "Soyad": "ÇEKEN",
      "Okul No": "41",
      "Sinif Sube": "5B"
    },
    {
      "Tc Kimlik": "71632168666",
      "Ad": "ZEYNEP",
      "Soyad": "KORKMAZ",
      "Okul No": "653",
      "Sinif Sube": "5B"
    }
  ],
  "Ogrenci_5. Sınıf _ C Şubesi": [
    {
      "Tc Kimlik": "35078244070",
      "Ad": "ABDULKADİR",
      "Soyad": "İMRAK",
      "Okul No": "6",
      "Sinif Sube": "5C"
    },
    {
      "Tc Kimlik": "33047312058",
      "Ad": "AY MİRAY",
      "Soyad": "ŞAHİN",
      "Okul No": "90",
      "Sinif Sube": "5C"
    },
    {
      "Tc Kimlik": "54910582644",
      "Ad": "BERAT DENİZ",
      "Soyad": "ESEN",
      "Okul No": "103",
      "Sinif Sube": "5C"
    },
    {
      "Tc Kimlik": "60178407216",
      "Ad": "ELİF",
      "Soyad": "BAYINDIR",
      "Okul No": "405",
      "Sinif Sube": "5C"
    },
    {
      "Tc Kimlik": "52465664334",
      "Ad": "ENİSE GÜL",
      "Soyad": "ADALMIŞ",
      "Okul No": "142",
      "Sinif Sube": "5C"
    },
    {
      "Tc Kimlik": "54481597474",
      "Ad": "FEHMİ",
      "Soyad": "YALÇIN",
      "Okul No": "494",
      "Sinif Sube": "5C"
    },
    {
      "Tc Kimlik": "99863702374",
      "Ad": "GUFRAN",
      "Soyad": "AVAD",
      "Okul No": "270",
      "Sinif Sube": "5C"
    },
    {
      "Tc Kimlik": "25586560366",
      "Ad": "HATİCE",
      "Soyad": "TİRİTOĞLU",
      "Okul No": "412",
      "Sinif Sube": "5C"
    },
    {
      "Tc Kimlik": "67435165872",
      "Ad": "İSLİM",
      "Soyad": "ÜSLÜ",
      "Okul No": "394",
      "Sinif Sube": "5C"
    },
    {
      "Tc Kimlik": "99290146000",
      "Ad": "İVAN",
      "Soyad": "HAMO",
      "Okul No": "315",
      "Sinif Sube": "5C"
    },
    {
      "Tc Kimlik": "65215239362",
      "Ad": "MUHAMMED HAKİM",
      "Soyad": "KIRĞIL",
      "Okul No": "1",
      "Sinif Sube": "5C"
    },
    {
      "Tc Kimlik": "57145508410",
      "Ad": "MUHAMMED HASAN",
      "Soyad": "DELEN",
      "Okul No": "171",
      "Sinif Sube": "5C"
    },
    {
      "Tc Kimlik": "39008113320",
      "Ad": "MUHAMMED OSMAN",
      "Soyad": "TAŞ",
      "Okul No": "491",
      "Sinif Sube": "5C"
    },
    {
      "Tc Kimlik": "38138142156",
      "Ad": "NİSA NUR",
      "Soyad": "DEMİRBİLEK",
      "Okul No": "520",
      "Sinif Sube": "5C"
    },
    {
      "Tc Kimlik": "99668361110",
      "Ad": "NUR HUDA",
      "Soyad": "SELUM",
      "Okul No": "200",
      "Sinif Sube": "5C"
    },
    {
      "Tc Kimlik": "99614191112",
      "Ad": "RENA",
      "Soyad": "HACHAMDO",
      "Okul No": "562",
      "Sinif Sube": "5C"
    },
    {
      "Tc Kimlik": "22079677426",
      "Ad": "ŞAHİN",
      "Soyad": "AÇIKALIN",
      "Okul No": "289",
      "Sinif Sube": "5C"
    },
    {
      "Tc Kimlik": "64330268608",
      "Ad": "VEYSEL",
      "Soyad": "ŞENKAN",
      "Okul No": "86",
      "Sinif Sube": "5C"
    },
    {
      "Tc Kimlik": "29336435768",
      "Ad": "ZAHİDE",
      "Soyad": "DALDA",
      "Okul No": "651",
      "Sinif Sube": "5C"
    },
    {
      "Tc Kimlik": "58303470280",
      "Ad": "ZELİHA",
      "Soyad": "MERAL",
      "Okul No": "392",
      "Sinif Sube": "5C"
    }
  ],
  "Ogrenci_6. Sınıf _ A Şubesi": [
    {
      "Tc Kimlik": "99115799954",
      "Ad": "ABDULLAH",
      "Soyad": "MIRRAVI",
      "Okul No": "12",
      "Sinif Sube": "6A"
    },
    {
      "Tc Kimlik": "30457608542",
      "Ad": "AHMETCAN",
      "Soyad": "ARSLAN",
      "Okul No": "18",
      "Sinif Sube": "6A"
    },
    {
      "Tc Kimlik": "20819719658",
      "Ad": "ASMİN",
      "Soyad": "ÇİÇEK",
      "Okul No": "21",
      "Sinif Sube": "6A"
    },
    {
      "Tc Kimlik": "99026107756",
      "Ad": "EMİR",
      "Soyad": "HAMO",
      "Okul No": "63",
      "Sinif Sube": "6A"
    },
    {
      "Tc Kimlik": "99395225150",
      "Ad": "FATMA",
      "Soyad": "ELHASAN",
      "Okul No": "107",
      "Sinif Sube": "6A"
    },
    {
      "Tc Kimlik": "39920082216",
      "Ad": "GÖKÇEN",
      "Soyad": "DEMİRCİOĞLU",
      "Okul No": "406",
      "Sinif Sube": "6A"
    },
    {
      "Tc Kimlik": "50065744180",
      "Ad": "GÖNÜL",
      "Soyad": "BABAYOĞURT",
      "Okul No": "408",
      "Sinif Sube": "6A"
    },
    {
      "Tc Kimlik": "99571529546",
      "Ad": "İBRAHİM",
      "Soyad": "GATİT",
      "Okul No": "203",
      "Sinif Sube": "6A"
    },
    {
      "Tc Kimlik": "23114642362",
      "Ad": "İBRAHİM HALİL",
      "Soyad": "GÜÇLÜ",
      "Okul No": "205",
      "Sinif Sube": "6A"
    },
    {
      "Tc Kimlik": "57955481330",
      "Ad": "İSLİM NİSA",
      "Soyad": "TÜMEN",
      "Okul No": "211",
      "Sinif Sube": "6A"
    },
    {
      "Tc Kimlik": "44143942056",
      "Ad": "İSLİM NUR",
      "Soyad": "KAPLAN",
      "Okul No": "213",
      "Sinif Sube": "6A"
    },
    {
      "Tc Kimlik": "40186288298",
      "Ad": "MEHMET ALİ",
      "Soyad": "BİNGÖL",
      "Okul No": "247",
      "Sinif Sube": "6A"
    },
    {
      "Tc Kimlik": "27965480876",
      "Ad": "MUHAMMED MUSTAFA",
      "Soyad": "EROĞLU",
      "Okul No": "53",
      "Sinif Sube": "6A"
    },
    {
      "Tc Kimlik": "99230293962",
      "Ad": "MUSTAFA",
      "Soyad": "ELAVVAD",
      "Okul No": "96",
      "Sinif Sube": "6A"
    },
    {
      "Tc Kimlik": "38786119968",
      "Ad": "NEHİR",
      "Soyad": "MERAL",
      "Okul No": "291",
      "Sinif Sube": "6A"
    },
    {
      "Tc Kimlik": "67684156676",
      "Ad": "TANER CAN",
      "Soyad": "İMRAK",
      "Okul No": "356",
      "Sinif Sube": "6A"
    },
    {
      "Tc Kimlik": "55711556544",
      "Ad": "YAHYA",
      "Soyad": "BÜYÜKKAPLAN",
      "Okul No": "360",
      "Sinif Sube": "6A"
    },
    {
      "Tc Kimlik": "99938939100",
      "Ad": "YUNUS",
      "Soyad": "ELZAKİ",
      "Okul No": "364",
      "Sinif Sube": "6A"
    },
    {
      "Tc Kimlik": "36907395956",
      "Ad": "YUSUF ENES",
      "Soyad": "KOZNAN",
      "Okul No": "366",
      "Sinif Sube": "6A"
    },
    {
      "Tc Kimlik": "64384266964",
      "Ad": "ZELİHA NUR",
      "Soyad": "SEÇEN",
      "Okul No": "84",
      "Sinif Sube": "6A"
    }
  ],
  "Ogrenci_6. Sınıf _ B Şubesi": [
    {
      "Tc Kimlik": "67975147444",
      "Ad": "AZAD AYAZ",
      "Soyad": "COŞKUN",
      "Okul No": "23",
      "Sinif Sube": "6B"
    },
    {
      "Tc Kimlik": "63064310812",
      "Ad": "AZİZ İBRAHİM",
      "Soyad": "ÇELENK",
      "Okul No": "24",
      "Sinif Sube": "6B"
    },
    {
      "Tc Kimlik": "20795719864",
      "Ad": "AZRA NUR",
      "Soyad": "BAZ",
      "Okul No": "20",
      "Sinif Sube": "6B"
    },
    {
      "Tc Kimlik": "68260137812",
      "Ad": "BELKIS NİSA",
      "Soyad": "KURT",
      "Okul No": "25",
      "Sinif Sube": "6B"
    },
    {
      "Tc Kimlik": "99652812260",
      "Ad": "EMİRA",
      "Soyad": "ALİ",
      "Okul No": "64",
      "Sinif Sube": "6B"
    },
    {
      "Tc Kimlik": "37280170918",
      "Ad": "ENES",
      "Soyad": "KILIÇ",
      "Okul No": "66",
      "Sinif Sube": "6B"
    },
    {
      "Tc Kimlik": "57868484268",
      "Ad": "EROL",
      "Soyad": "ATMACA",
      "Okul No": "78",
      "Sinif Sube": "6B"
    },
    {
      "Tc Kimlik": "28739454888",
      "Ad": "FATMA",
      "Soyad": "GERÇEK",
      "Okul No": "75",
      "Sinif Sube": "6B"
    },
    {
      "Tc Kimlik": "99395130324",
      "Ad": "FATTUM",
      "Soyad": "ELALUSE",
      "Okul No": "36",
      "Sinif Sube": "6B"
    },
    {
      "Tc Kimlik": "46840852164",
      "Ad": "HASAN MERT",
      "Soyad": "KILIÇ",
      "Okul No": "58",
      "Sinif Sube": "6B"
    },
    {
      "Tc Kimlik": "53773621194",
      "Ad": "HATİCE KÜBRA",
      "Soyad": "BUDAK",
      "Okul No": "167",
      "Sinif Sube": "6B"
    },
    {
      "Tc Kimlik": "72127008658",
      "Ad": "HAVVA NUR",
      "Soyad": "BULUZ",
      "Okul No": "175",
      "Sinif Sube": "6B"
    },
    {
      "Tc Kimlik": "43897949564",
      "Ad": "MAHMUT",
      "Soyad": "KARATAŞ",
      "Okul No": "243",
      "Sinif Sube": "6B"
    },
    {
      "Tc Kimlik": "31496363072",
      "Ad": "NECİP TAHİR",
      "Soyad": "TÜMEN",
      "Okul No": "287",
      "Sinif Sube": "6B"
    },
    {
      "Tc Kimlik": "99653200172",
      "Ad": "ÖMER",
      "Soyad": "HACCAN",
      "Okul No": "311",
      "Sinif Sube": "6B"
    },
    {
      "Tc Kimlik": "67114175710",
      "Ad": "RAHİME İKRA",
      "Soyad": "KANLIEL",
      "Okul No": "67",
      "Sinif Sube": "6B"
    },
    {
      "Tc Kimlik": "99002605832",
      "Ad": "RİTAC",
      "Soyad": "ELHEMMO",
      "Okul No": "324",
      "Sinif Sube": "6B"
    },
    {
      "Tc Kimlik": "99172794794",
      "Ad": "SÜNDÜZ",
      "Soyad": "DERVIŞ",
      "Okul No": "349",
      "Sinif Sube": "6B"
    },
    {
      "Tc Kimlik": "19244771522",
      "Ad": "TUBA",
      "Soyad": "POLAT",
      "Okul No": "11",
      "Sinif Sube": "6B"
    },
    {
      "Tc Kimlik": "99332191906",
      "Ad": "VELA",
      "Soyad": "EL NAHSAN",
      "Okul No": "244",
      "Sinif Sube": "6B"
    }
  ],
  "Ogrenci_6. Sınıf _ C Şubesi": [
    {
      "Tc Kimlik": "32045344702",
      "Ad": "ABDULLAH",
      "Soyad": "TUNGAÇ",
      "Okul No": "13",
      "Sinif Sube": "6C"
    },
    {
      "Tc Kimlik": "99179896132",
      "Ad": "ABDULLATİF",
      "Soyad": "DEDEN",
      "Okul No": "102",
      "Sinif Sube": "6C"
    },
    {
      "Tc Kimlik": "38951114866",
      "Ad": "ALİ",
      "Soyad": "SÜRGÜVENÇ",
      "Okul No": "99",
      "Sinif Sube": "6C"
    },
    {
      "Tc Kimlik": "45451898486",
      "Ad": "AYNUR ZELİHA",
      "Soyad": "DEMİRBİLEK",
      "Okul No": "22",
      "Sinif Sube": "6C"
    },
    {
      "Tc Kimlik": "20942725786",
      "Ad": "BÜŞRA NUR",
      "Soyad": "YAŞAR",
      "Okul No": "39",
      "Sinif Sube": "6C"
    },
    {
      "Tc Kimlik": "61681356770",
      "Ad": "ECRİN",
      "Soyad": "KUŞKU",
      "Okul No": "46",
      "Sinif Sube": "6C"
    },
    {
      "Tc Kimlik": "99563239668",
      "Ad": "FATMA",
      "Soyad": "DADAN",
      "Okul No": "32",
      "Sinif Sube": "6C"
    },
    {
      "Tc Kimlik": "10899192908",
      "Ad": "HALİL İBRAHİM",
      "Soyad": "KORKMAZ",
      "Okul No": "83",
      "Sinif Sube": "6C"
    },
    {
      "Tc Kimlik": "64819253064",
      "Ad": "HAMZA",
      "Soyad": "EROĞLU",
      "Okul No": "378",
      "Sinif Sube": "6C"
    },
    {
      "Tc Kimlik": "37388166844",
      "Ad": "HÜSEYİN KENAN",
      "Soyad": "KARTAL",
      "Okul No": "196",
      "Sinif Sube": "6C"
    },
    {
      "Tc Kimlik": "99599572128",
      "Ad": "İSMAİL",
      "Soyad": "İBO",
      "Okul No": "220",
      "Sinif Sube": "6C"
    },
    {
      "Tc Kimlik": "99385790606",
      "Ad": "MUHAMMED",
      "Soyad": "İBRAHİM",
      "Okul No": "274",
      "Sinif Sube": "6C"
    },
    {
      "Tc Kimlik": "99080677882",
      "Ad": "MUHAMMED",
      "Soyad": "SAİD",
      "Okul No": "162",
      "Sinif Sube": "6C"
    },
    {
      "Tc Kimlik": "46027092550",
      "Ad": "MUHAMMED ENES",
      "Soyad": "ALTUNTAŞ",
      "Okul No": "100",
      "Sinif Sube": "6C"
    },
    {
      "Tc Kimlik": "44938914978",
      "Ad": "MUHAMMET",
      "Soyad": "ESEN",
      "Okul No": "277",
      "Sinif Sube": "6C"
    },
    {
      "Tc Kimlik": "70693056646",
      "Ad": "MURAT",
      "Soyad": "DÜLEK",
      "Okul No": "282",
      "Sinif Sube": "6C"
    },
    {
      "Tc Kimlik": "14429752464",
      "Ad": "NERGİZ DİCLE",
      "Soyad": "DAĞDELEN",
      "Okul No": "293",
      "Sinif Sube": "6C"
    },
    {
      "Tc Kimlik": "15065910614",
      "Ad": "PERİHAN SU",
      "Soyad": "KARTAL",
      "Okul No": "317",
      "Sinif Sube": "6C"
    },
    {
      "Tc Kimlik": "42254004854",
      "Ad": "SÜMEYYE MERYEM",
      "Soyad": "KAYA",
      "Okul No": "380",
      "Sinif Sube": "6C"
    },
    {
      "Tc Kimlik": "41650248886",
      "Ad": "TUĞBA",
      "Soyad": "HASAN",
      "Okul No": "54",
      "Sinif Sube": "6C"
    }
  ],
  "Ogrenci_7. Sınıf _ A Şubesi": [
    {
      "Tc Kimlik": "99500551914",
      "Ad": "AHMED",
      "Soyad": "ELMUHAMED",
      "Okul No": "108",
      "Sinif Sube": "7A"
    },
    {
      "Tc Kimlik": "99611236298",
      "Ad": "AHMED",
      "Soyad": "MERRAŞİ",
      "Okul No": "109",
      "Sinif Sube": "7A"
    },
    {
      "Tc Kimlik": "25901549588",
      "Ad": "AHMET MUHAMMET",
      "Soyad": "UZUN",
      "Okul No": "117",
      "Sinif Sube": "7A"
    },
    {
      "Tc Kimlik": "25001579638",
      "Ad": "ASMİN",
      "Soyad": "MURAT",
      "Okul No": "129",
      "Sinif Sube": "7A"
    },
    {
      "Tc Kimlik": "49399766340",
      "Ad": "BERAT MÜFTAH",
      "Soyad": "OKLUER",
      "Okul No": "152",
      "Sinif Sube": "7A"
    },
    {
      "Tc Kimlik": "25319568942",
      "Ad": "CEYLİN GÜL",
      "Soyad": "UZUN",
      "Okul No": "158",
      "Sinif Sube": "7A"
    },
    {
      "Tc Kimlik": "18890783712",
      "Ad": "FATMANUR",
      "Soyad": "İMRAK",
      "Okul No": "518",
      "Sinif Sube": "7A"
    },
    {
      "Tc Kimlik": "27386500078",
      "Ad": "GAZAL",
      "Soyad": "YALÇIN",
      "Okul No": "221",
      "Sinif Sube": "7A"
    },
    {
      "Tc Kimlik": "46384866870",
      "Ad": "HALİL İBRAHİM",
      "Soyad": "ŞİNİKÇİ",
      "Okul No": "230",
      "Sinif Sube": "7A"
    },
    {
      "Tc Kimlik": "56482530092",
      "Ad": "HASAN",
      "Soyad": "YEŞİLTEPELER",
      "Okul No": "57",
      "Sinif Sube": "7A"
    },
    {
      "Tc Kimlik": "21611692750",
      "Ad": "HATİCE KÜBRA",
      "Soyad": "YENİÇELEN",
      "Okul No": "241",
      "Sinif Sube": "7A"
    },
    {
      "Tc Kimlik": "66700189568",
      "Ad": "MUHAMMED MUSTAFA",
      "Soyad": "AÇIKCAN",
      "Okul No": "403",
      "Sinif Sube": "7A"
    },
    {
      "Tc Kimlik": "99085802326",
      "Ad": "MUHAMMET",
      "Soyad": "ALBEYYUŞ",
      "Okul No": "294",
      "Sinif Sube": "7A"
    },
    {
      "Tc Kimlik": "72322002390",
      "Ad": "MUSTAFA",
      "Soyad": "SARIBAŞAK",
      "Okul No": "297",
      "Sinif Sube": "7A"
    },
    {
      "Tc Kimlik": "43729955138",
      "Ad": "MÜSLÜM",
      "Soyad": "SERİN",
      "Okul No": "302",
      "Sinif Sube": "7A"
    },
    {
      "Tc Kimlik": "71671024312",
      "Ad": "NEBİ",
      "Soyad": "KARADAL",
      "Okul No": "303",
      "Sinif Sube": "7A"
    },
    {
      "Tc Kimlik": "70180073590",
      "Ad": "ORHAN",
      "Soyad": "KAYA",
      "Okul No": "306",
      "Sinif Sube": "7A"
    },
    {
      "Tc Kimlik": "40202073020",
      "Ad": "ÖZLEM NUR",
      "Soyad": "AKYAVUZ",
      "Okul No": "313",
      "Sinif Sube": "7A"
    },
    {
      "Tc Kimlik": "71095043098",
      "Ad": "RAMAZAN",
      "Soyad": "BİLİŞİK",
      "Okul No": "316",
      "Sinif Sube": "7A"
    },
    {
      "Tc Kimlik": "29372433902",
      "Ad": "SAMİ FIRAT",
      "Soyad": "ARSLANTAŞ",
      "Okul No": "370",
      "Sinif Sube": "7A"
    },
    {
      "Tc Kimlik": "99917256952",
      "Ad": "SEMAR",
      "Soyad": "AHMED",
      "Okul No": "500",
      "Sinif Sube": "7A"
    },
    {
      "Tc Kimlik": "25889549976",
      "Ad": "TUANA NUR",
      "Soyad": "UZUN",
      "Okul No": "334",
      "Sinif Sube": "7A"
    },
    {
      "Tc Kimlik": "99638367944",
      "Ad": "YASMİN",
      "Soyad": "HACHAMDO",
      "Okul No": "352",
      "Sinif Sube": "7A"
    },
    {
      "Tc Kimlik": "40291301202",
      "Ad": "ZEHRA",
      "Soyad": "UÇAR",
      "Okul No": "348",
      "Sinif Sube": "7A"
    }
  ],
  "Ogrenci_7. Sınıf _ B Şubesi": [
    {
      "Tc Kimlik": "64201272970",
      "Ad": "ABDULLAH SAİT",
      "Soyad": "KARA",
      "Okul No": "119",
      "Sinif Sube": "7B"
    },
    {
      "Tc Kimlik": "29294436548",
      "Ad": "AYŞE NAZ",
      "Soyad": "ARSLANTAŞ",
      "Okul No": "383",
      "Sinif Sube": "7B"
    },
    {
      "Tc Kimlik": "69988080244",
      "Ad": "BİLAL",
      "Soyad": "DEMİR",
      "Okul No": "156",
      "Sinif Sube": "7B"
    },
    {
      "Tc Kimlik": "99818128624",
      "Ad": "CUMA",
      "Soyad": "EL HALAF",
      "Okul No": "160",
      "Sinif Sube": "7B"
    },
    {
      "Tc Kimlik": "99020028088",
      "Ad": "DUA",
      "Soyad": "SUVEYD",
      "Okul No": "166",
      "Sinif Sube": "7B"
    },
    {
      "Tc Kimlik": "43801952956",
      "Ad": "EFE",
      "Soyad": "TİRİTOĞLU",
      "Okul No": "147",
      "Sinif Sube": "7B"
    },
    {
      "Tc Kimlik": "50650724740",
      "Ad": "ELİF ADA",
      "Soyad": "SANAĞ",
      "Okul No": "501",
      "Sinif Sube": "7B"
    },
    {
      "Tc Kimlik": "25297802724",
      "Ad": "EMİNE",
      "Soyad": "DİKİLİTAŞ",
      "Okul No": "523",
      "Sinif Sube": "7B"
    },
    {
      "Tc Kimlik": "71200039596",
      "Ad": "FATMA NUR",
      "Soyad": "KORKMAZ",
      "Okul No": "204",
      "Sinif Sube": "7B"
    },
    {
      "Tc Kimlik": "58810452878",
      "Ad": "FERMANDAR EGİT",
      "Soyad": "BOZKURT",
      "Okul No": "219",
      "Sinif Sube": "7B"
    },
    {
      "Tc Kimlik": "57826486006",
      "Ad": "HAYRUNNİSA",
      "Soyad": "İNCEDAL",
      "Okul No": "996",
      "Sinif Sube": "7B"
    },
    {
      "Tc Kimlik": "30179407102",
      "Ad": "İBRAHİM HALİL",
      "Soyad": "AÇIKALIN",
      "Okul No": "257",
      "Sinif Sube": "7B"
    },
    {
      "Tc Kimlik": "41204040140",
      "Ad": "KADER",
      "Soyad": "BAYRAM",
      "Okul No": "307",
      "Sinif Sube": "7B"
    },
    {
      "Tc Kimlik": "27524495334",
      "Ad": "MEHMET ALİ",
      "Soyad": "GÜÇLÜ",
      "Okul No": "269",
      "Sinif Sube": "7B"
    },
    {
      "Tc Kimlik": "17468830704",
      "Ad": "MUHAMMED ALİ",
      "Soyad": "ASLAN",
      "Okul No": "393",
      "Sinif Sube": "7B"
    },
    {
      "Tc Kimlik": "21545694578",
      "Ad": "MUSTAFA",
      "Soyad": "BULUT",
      "Okul No": "295",
      "Sinif Sube": "7B"
    },
    {
      "Tc Kimlik": "17012845918",
      "Ad": "MUSTAFA YİĞİT",
      "Soyad": "DURMAZ",
      "Okul No": "299",
      "Sinif Sube": "7B"
    },
    {
      "Tc Kimlik": "99611711498",
      "Ad": "NEDA",
      "Soyad": "ALMİRİ",
      "Okul No": "48",
      "Sinif Sube": "7B"
    },
    {
      "Tc Kimlik": "69181107632",
      "Ad": "SALİH",
      "Soyad": "KARADAL",
      "Okul No": "323",
      "Sinif Sube": "7B"
    },
    {
      "Tc Kimlik": "72232005146",
      "Ad": "SEVGİ",
      "Soyad": "ARSLAN",
      "Okul No": "327",
      "Sinif Sube": "7B"
    },
    {
      "Tc Kimlik": "68977113956",
      "Ad": "TUNA EGEMEN",
      "Soyad": "AYILMAZER",
      "Okul No": "335",
      "Sinif Sube": "7B"
    },
    {
      "Tc Kimlik": "53590636456",
      "Ad": "ÜMİT",
      "Soyad": "YAMUKTU",
      "Okul No": "337",
      "Sinif Sube": "7B"
    },
    {
      "Tc Kimlik": "61495363568",
      "Ad": "ZİLAN",
      "Soyad": "SAĞIR",
      "Okul No": "347",
      "Sinif Sube": "7B"
    }
  ],
  "Ogrenci_7. Sınıf _ C Şubesi": [
    {
      "Tc Kimlik": "42574993654",
      "Ad": "AYŞE",
      "Soyad": "ELMAOĞLU",
      "Okul No": "139",
      "Sinif Sube": "7C"
    },
    {
      "Tc Kimlik": "68824118738",
      "Ad": "BAĞDAGÜL",
      "Soyad": "UYGUNER",
      "Okul No": "301",
      "Sinif Sube": "7C"
    },
    {
      "Tc Kimlik": "71329035370",
      "Ad": "BÜNYAMİN",
      "Soyad": "ŞAHİN",
      "Okul No": "400",
      "Sinif Sube": "7C"
    },
    {
      "Tc Kimlik": "68671124050",
      "Ad": "EBUBEKİR",
      "Soyad": "POLAT",
      "Okul No": "169",
      "Sinif Sube": "7C"
    },
    {
      "Tc Kimlik": "43573960524",
      "Ad": "ELİF NUR",
      "Soyad": "ORUZ",
      "Okul No": "179",
      "Sinif Sube": "7C"
    },
    {
      "Tc Kimlik": "28820452304",
      "Ad": "FATMA ECRİN",
      "Soyad": "ARSLANTAŞ",
      "Okul No": "372",
      "Sinif Sube": "7C"
    },
    {
      "Tc Kimlik": "67513162472",
      "Ad": "FATMA NUR",
      "Soyad": "UYGUNER",
      "Okul No": "209",
      "Sinif Sube": "7C"
    },
    {
      "Tc Kimlik": "20413959856",
      "Ad": "GÜLİSTAN",
      "Soyad": "ATAŞ",
      "Okul No": "519",
      "Sinif Sube": "7C"
    },
    {
      "Tc Kimlik": "99788255610",
      "Ad": "HALİD",
      "Soyad": "NASEN",
      "Okul No": "503",
      "Sinif Sube": "7C"
    },
    {
      "Tc Kimlik": "45838885436",
      "Ad": "HASAN HÜSEYİN",
      "Soyad": "DEMİR",
      "Okul No": "851",
      "Sinif Sube": "7C"
    },
    {
      "Tc Kimlik": "99092677436",
      "Ad": "HENE",
      "Soyad": "SAİD",
      "Okul No": "513",
      "Sinif Sube": "7C"
    },
    {
      "Tc Kimlik": "99641367870",
      "Ad": "HUSEM",
      "Soyad": "HACHAMDO",
      "Okul No": "645",
      "Sinif Sube": "7C"
    },
    {
      "Tc Kimlik": "40304212792",
      "Ad": "İBRAHİM HALİL",
      "Soyad": "AKYAVUZ",
      "Okul No": "499",
      "Sinif Sube": "7C"
    },
    {
      "Tc Kimlik": "24044611732",
      "Ad": "İBRAHİM HALİL",
      "Soyad": "ÖZÜPERK",
      "Okul No": "258",
      "Sinif Sube": "7C"
    },
    {
      "Tc Kimlik": "63106310190",
      "Ad": "İLAYDA",
      "Soyad": "ÖZDİLEK",
      "Okul No": "516",
      "Sinif Sube": "7C"
    },
    {
      "Tc Kimlik": "37868150806",
      "Ad": "KÜBRA",
      "Soyad": "KILIÇ",
      "Okul No": "262",
      "Sinif Sube": "7C"
    },
    {
      "Tc Kimlik": "33442521666",
      "Ad": "MİKAİL CAN",
      "Soyad": "TOKMAK",
      "Okul No": "280",
      "Sinif Sube": "7C"
    },
    {
      "Tc Kimlik": "34727255252",
      "Ad": "MUHAMMED BİLAL",
      "Soyad": "ÖZKAN",
      "Okul No": "286",
      "Sinif Sube": "7C"
    },
    {
      "Tc Kimlik": "35303236566",
      "Ad": "MUHAMMED EMİR",
      "Soyad": "ÖCALAN",
      "Okul No": "82",
      "Sinif Sube": "7C"
    },
    {
      "Tc Kimlik": "32135341956",
      "Ad": "MUHAMMED NECİP",
      "Soyad": "TÜMEN",
      "Okul No": "288",
      "Sinif Sube": "7C"
    },
    {
      "Tc Kimlik": "99818254668",
      "Ad": "MUSTAFA",
      "Soyad": "NASEN",
      "Okul No": "508",
      "Sinif Sube": "7C"
    },
    {
      "Tc Kimlik": "35249237948",
      "Ad": "SALİHA NUR",
      "Soyad": "DEMİRCİOĞLU",
      "Okul No": "514",
      "Sinif Sube": "7C"
    },
    {
      "Tc Kimlik": "20786720282",
      "Ad": "SEVDA NUR",
      "Soyad": "KANKILIÇ",
      "Okul No": "325",
      "Sinif Sube": "7C"
    },
    {
      "Tc Kimlik": "65026389324",
      "Ad": "UMUT BARAN",
      "Soyad": "TURAN",
      "Okul No": "401",
      "Sinif Sube": "7C"
    },
    {
      "Tc Kimlik": "21662690934",
      "Ad": "VAKKAS EREN",
      "Soyad": "ERDOĞAN",
      "Okul No": "340",
      "Sinif Sube": "7C"
    }
  ],
  "Ogrenci_8. Sınıf _ A Şubesi": [
    {
      "Tc Kimlik": "99611711870",
      "Ad": "AHMED",
      "Soyad": "AVAD",
      "Okul No": "29",
      "Sinif Sube": "8A"
    },
    {
      "Tc Kimlik": "99757539970",
      "Ad": "AHMED",
      "Soyad": "ELKATUF",
      "Okul No": "110",
      "Sinif Sube": "8A"
    },
    {
      "Tc Kimlik": "40964047970",
      "Ad": "AHMET",
      "Soyad": "SAVAŞ",
      "Okul No": "104",
      "Sinif Sube": "8A"
    },
    {
      "Tc Kimlik": "25676556934",
      "Ad": "AYSEL",
      "Soyad": "ULUSOY",
      "Okul No": "148",
      "Sinif Sube": "8A"
    },
    {
      "Tc Kimlik": "47116842520",
      "Ad": "BÜNYAMİN",
      "Soyad": "SAĞIR",
      "Okul No": "37",
      "Sinif Sube": "8A"
    },
    {
      "Tc Kimlik": "99766724268",
      "Ad": "DUA",
      "Soyad": "ĞIREYBI",
      "Okul No": "40",
      "Sinif Sube": "8A"
    },
    {
      "Tc Kimlik": "62728322260",
      "Ad": "ELİF",
      "Soyad": "DEMİR",
      "Okul No": "250",
      "Sinif Sube": "8A"
    },
    {
      "Tc Kimlik": "99587712222",
      "Ad": "EMİNE",
      "Soyad": "ALMİRİ",
      "Okul No": "130",
      "Sinif Sube": "8A"
    },
    {
      "Tc Kimlik": "23852618308",
      "Ad": "FATMA",
      "Soyad": "KAYAOKAY",
      "Okul No": "47",
      "Sinif Sube": "8A"
    },
    {
      "Tc Kimlik": "18665790822",
      "Ad": "FEHİMENUR",
      "Soyad": "ORUZ",
      "Okul No": "49",
      "Sinif Sube": "8A"
    },
    {
      "Tc Kimlik": "99881181410",
      "Ad": "İBRAHİM",
      "Soyad": "DADAN",
      "Okul No": "62",
      "Sinif Sube": "8A"
    },
    {
      "Tc Kimlik": "63223305802",
      "Ad": "İLAYDA",
      "Soyad": "BAZ",
      "Okul No": "120",
      "Sinif Sube": "8A"
    },
    {
      "Tc Kimlik": "14933915140",
      "Ad": "İSLİM",
      "Soyad": "ARSLAN",
      "Okul No": "65",
      "Sinif Sube": "8A"
    },
    {
      "Tc Kimlik": "18323802546",
      "Ad": "KAZIM SÜFYAN",
      "Soyad": "ÇETİN",
      "Okul No": "71",
      "Sinif Sube": "8A"
    },
    {
      "Tc Kimlik": "45094910002",
      "Ad": "MAHMUT",
      "Soyad": "MERAL",
      "Okul No": "74",
      "Sinif Sube": "8A"
    },
    {
      "Tc Kimlik": "31124375736",
      "Ad": "MEHMET ALİ",
      "Soyad": "KURT",
      "Okul No": "76",
      "Sinif Sube": "8A"
    },
    {
      "Tc Kimlik": "49234772390",
      "Ad": "MEHMET MUSTAFA",
      "Soyad": "CANLI",
      "Okul No": "4",
      "Sinif Sube": "8A"
    },
    {
      "Tc Kimlik": "53749621692",
      "Ad": "MUSTAFA",
      "Soyad": "ARIKAN",
      "Okul No": "116",
      "Sinif Sube": "8A"
    },
    {
      "Tc Kimlik": "61495363186",
      "Ad": "SALİH",
      "Soyad": "BİLİŞİK",
      "Okul No": "226",
      "Sinif Sube": "8A"
    },
    {
      "Tc Kimlik": "34112276466",
      "Ad": "SEYFETTİN CAN",
      "Soyad": "İMRAK",
      "Okul No": "229",
      "Sinif Sube": "8A"
    },
    {
      "Tc Kimlik": "99920156270",
      "Ad": "YUSUF",
      "Soyad": "AVAD",
      "Okul No": "444",
      "Sinif Sube": "8A"
    },
    {
      "Tc Kimlik": "15746888546",
      "Ad": "ZEYNEP ZENAN",
      "Soyad": "KANLIEL",
      "Okul No": "192",
      "Sinif Sube": "8A"
    }
  ],
  "Ogrenci_8. Sınıf _ B Şubesi": [
    {
      "Tc Kimlik": "47113843056",
      "Ad": "ABDULLAH",
      "Soyad": "KILIÇ",
      "Okul No": "195",
      "Sinif Sube": "8B"
    },
    {
      "Tc Kimlik": "99035239820",
      "Ad": "ABDURRAHMAN",
      "Soyad": "ELİSA",
      "Okul No": "27",
      "Sinif Sube": "8B"
    },
    {
      "Tc Kimlik": "99347043672",
      "Ad": "AHMED",
      "Soyad": "AHMED",
      "Okul No": "509",
      "Sinif Sube": "8B"
    },
    {
      "Tc Kimlik": "99074349870",
      "Ad": "AHMED",
      "Soyad": "ELHUMEYDİ",
      "Okul No": "284",
      "Sinif Sube": "8B"
    },
    {
      "Tc Kimlik": "14732922516",
      "Ad": "AHMET",
      "Soyad": "ÇİFÇİ",
      "Okul No": "17",
      "Sinif Sube": "8B"
    },
    {
      "Tc Kimlik": "66832185278",
      "Ad": "BERAT",
      "Soyad": "SARI",
      "Okul No": "34",
      "Sinif Sube": "8B"
    },
    {
      "Tc Kimlik": "57718489504",
      "Ad": "BERAT",
      "Soyad": "SEÇEN",
      "Okul No": "190",
      "Sinif Sube": "8B"
    },
    {
      "Tc Kimlik": "50425732222",
      "Ad": "CEREN",
      "Soyad": "SAĞIR",
      "Okul No": "38",
      "Sinif Sube": "8B"
    },
    {
      "Tc Kimlik": "36575194448",
      "Ad": "ELİF",
      "Soyad": "KAPLAN",
      "Okul No": "42",
      "Sinif Sube": "8B"
    },
    {
      "Tc Kimlik": "30668390960",
      "Ad": "ESMA NUR",
      "Soyad": "GÜZEL",
      "Okul No": "45",
      "Sinif Sube": "8B"
    },
    {
      "Tc Kimlik": "68995113754",
      "Ad": "FATOŞ",
      "Soyad": "ALTUNTAŞ",
      "Okul No": "155",
      "Sinif Sube": "8B"
    },
    {
      "Tc Kimlik": "64117275676",
      "Ad": "FERHAT",
      "Soyad": "KOT",
      "Okul No": "50",
      "Sinif Sube": "8B"
    },
    {
      "Tc Kimlik": "69766087830",
      "Ad": "MEHMET",
      "Soyad": "ATMACA",
      "Okul No": "253",
      "Sinif Sube": "8B"
    },
    {
      "Tc Kimlik": "99989316172",
      "Ad": "MUHAMMED",
      "Soyad": "DERVİŞ",
      "Okul No": "81",
      "Sinif Sube": "8B"
    },
    {
      "Tc Kimlik": "30164408084",
      "Ad": "MUHAMMED EFE",
      "Soyad": "KILIÇ",
      "Okul No": "223",
      "Sinif Sube": "8B"
    },
    {
      "Tc Kimlik": "58843451862",
      "Ad": "MUHAMMED MUSTAFA",
      "Soyad": "AKYAVUZ",
      "Okul No": "105",
      "Sinif Sube": "8B"
    },
    {
      "Tc Kimlik": "99556787534",
      "Ad": "MUSTAFA",
      "Soyad": "EL HASAN",
      "Okul No": "271",
      "Sinif Sube": "8B"
    },
    {
      "Tc Kimlik": "71422032696",
      "Ad": "MÜSLÜM EFE",
      "Soyad": "ASLAN",
      "Okul No": "135",
      "Sinif Sube": "8B"
    },
    {
      "Tc Kimlik": "36179206868",
      "Ad": "SADİN ENES",
      "Soyad": "BALOĞLU",
      "Okul No": "312",
      "Sinif Sube": "8B"
    },
    {
      "Tc Kimlik": "36776187218",
      "Ad": "YÜKSEL",
      "Soyad": "ASLAN",
      "Okul No": "459",
      "Sinif Sube": "8B"
    },
    {
      "Tc Kimlik": "70378067288",
      "Ad": "ZEHRA",
      "Soyad": "BULUZ",
      "Okul No": "504",
      "Sinif Sube": "8B"
    },
    {
      "Tc Kimlik": "20288737108",
      "Ad": "ZEYNEP",
      "Soyad": "GEZER",
      "Okul No": "210",
      "Sinif Sube": "8B"
    },
    {
      "Tc Kimlik": "71152041944",
      "Ad": "ZEYNEP",
      "Soyad": "GÜZEL",
      "Okul No": "528",
      "Sinif Sube": "8B"
    }
  ],
  "Ogrenci_8. Sınıf _ C Şubesi": [
    {
      "Tc Kimlik": "51301703572",
      "Ad": "ABDULLAH",
      "Soyad": "DAĞDELEN",
      "Okul No": "15",
      "Sinif Sube": "8C"
    },
    {
      "Tc Kimlik": "35159241066",
      "Ad": "BERAT",
      "Soyad": "YİĞİT",
      "Okul No": "125",
      "Sinif Sube": "8C"
    },
    {
      "Tc Kimlik": "58435465628",
      "Ad": "BEYZANUR",
      "Soyad": "AYKUT",
      "Okul No": "481",
      "Sinif Sube": "8C"
    },
    {
      "Tc Kimlik": "19664758028",
      "Ad": "EYLÜL",
      "Soyad": "DALKIRAN",
      "Okul No": "194",
      "Sinif Sube": "8C"
    },
    {
      "Tc Kimlik": "99649812334",
      "Ad": "FİDA",
      "Soyad": "ALİ",
      "Okul No": "52",
      "Sinif Sube": "8C"
    },
    {
      "Tc Kimlik": "62083343672",
      "Ad": "HANIMGÜL",
      "Soyad": "IŞIK",
      "Okul No": "55",
      "Sinif Sube": "8C"
    },
    {
      "Tc Kimlik": "29147441798",
      "Ad": "HÜSEYİN",
      "Soyad": "TUNGAÇ",
      "Okul No": "61",
      "Sinif Sube": "8C"
    },
    {
      "Tc Kimlik": "44401932782",
      "Ad": "LEYLANUR",
      "Soyad": "DAĞDELEN",
      "Okul No": "72",
      "Sinif Sube": "8C"
    },
    {
      "Tc Kimlik": "70810052520",
      "Ad": "MEHMET",
      "Soyad": "AYILMAZER",
      "Okul No": "505",
      "Sinif Sube": "8C"
    },
    {
      "Tc Kimlik": "51082710004",
      "Ad": "MEHMETCAN",
      "Soyad": "YİĞİT",
      "Okul No": "80",
      "Sinif Sube": "8C"
    },
    {
      "Tc Kimlik": "70258071190",
      "Ad": "MUHAMMED",
      "Soyad": "TAŞOĞLU",
      "Okul No": "106",
      "Sinif Sube": "8C"
    },
    {
      "Tc Kimlik": "23024645422",
      "Ad": "MUHAMMED MUSTAFA",
      "Soyad": "OPAK",
      "Okul No": "186",
      "Sinif Sube": "8C"
    },
    {
      "Tc Kimlik": "39176107138",
      "Ad": "MÜSLÜM",
      "Soyad": "GÜLEÇ",
      "Okul No": "474",
      "Sinif Sube": "8C"
    },
    {
      "Tc Kimlik": "18533795416",
      "Ad": "NEHİR SELEN",
      "Soyad": "GÜÇLÜ",
      "Okul No": "136",
      "Sinif Sube": "8C"
    },
    {
      "Tc Kimlik": "49741755282",
      "Ad": "ÖZKAN",
      "Soyad": "DEMİR",
      "Okul No": "26",
      "Sinif Sube": "8C"
    },
    {
      "Tc Kimlik": "99457858678",
      "Ad": "SAMIR",
      "Soyad": "ELHASAN",
      "Okul No": "227",
      "Sinif Sube": "8C"
    },
    {
      "Tc Kimlik": "38039145676",
      "Ad": "SEYFEDDİN CAN",
      "Soyad": "İMRAK",
      "Okul No": "228",
      "Sinif Sube": "8C"
    },
    {
      "Tc Kimlik": "99725621584",
      "Ad": "SİDRA",
      "Soyad": "EL HASAN",
      "Okul No": "151",
      "Sinif Sube": "8C"
    },
    {
      "Tc Kimlik": "47992813058",
      "Ad": "TUĞBA",
      "Soyad": "MERMER",
      "Okul No": "236",
      "Sinif Sube": "8C"
    },
    {
      "Tc Kimlik": "63547295360",
      "Ad": "TUĞBANUR",
      "Soyad": "KAYA",
      "Okul No": "368",
      "Sinif Sube": "8C"
    },
    {
      "Tc Kimlik": "15005913408",
      "Ad": "YALÇIN",
      "Soyad": "ÇİFÇİ",
      "Okul No": "19",
      "Sinif Sube": "8C"
    },
    {
      "Tc Kimlik": "48940782068",
      "Ad": "YASİN",
      "Soyad": "SAVAŞ",
      "Okul No": "206",
      "Sinif Sube": "8C"
    }
  ]
}